[{"tag":"","latitude":"46.484863","longitude":"30.734532","speed":20,"pause":0,"$$hashKey":"object:25"},{"latitude":46.484567499614705,"longitude":30.734387126050024,"speed":20,"pause":0,"$$hashKey":"object:26"},{"latitude":46.484334794226484,"longitude":30.73408402071368,"speed":20,"pause":0,"$$hashKey":"object:27"},{"latitude":46.484030061995185,"longitude":30.73324045905906,"speed":20,"pause":0,"$$hashKey":"object:28"},{"latitude":46.484397581264176,"longitude":30.733426865287015,"speed":20,"pause":0,"$$hashKey":"object:29"},{"latitude":46.48515845776848,"longitude":30.73448895534125,"speed":20,"pause":0,"$$hashKey":"object:30"},{"latitude":46.48640687369445,"longitude":30.736216234854055,"speed":20,"pause":0,"$$hashKey":"object:31"},{"latitude":46.48583972392902,"longitude":30.73262486642011,"speed":20,"pause":0,"$$hashKey":"object:32"},{"latitude":46.48451666850578,"longitude":30.730824108127536,"speed":20,"pause":0,"$$hashKey":"object:33"},{"latitude":46.482691257489044,"longitude":30.730010478405575,"speed":20,"pause":0,"$$hashKey":"object:34"},{"latitude":46.483806021916635,"longitude":30.728939390902724,"speed":20,"pause":0,"$$hashKey":"object:35"},{"latitude":46.482970465654525,"longitude":30.725014376836725,"speed":20,"pause":0,"$$hashKey":"object:36"},{"latitude":46.48370507757355,"longitude":30.725500691367415,"speed":20,"pause":0,"$$hashKey":"object:37"},{"latitude":46.48444632359083,"longitude":30.72689632537515,"speed":20,"pause":0,"$$hashKey":"object:38"},{"latitude":46.48439587068983,"longitude":30.726145752140496,"speed":20,"pause":0,"$$hashKey":"object:39"},{"latitude":46.48498072333061,"longitude":30.725266424867527,"speed":20,"pause":0,"$$hashKey":"object:40"},{"latitude":46.485057111887876,"longitude":30.72467721272801,"speed":20,"pause":0,"$$hashKey":"object:41"},{"latitude":46.485621055260175,"longitude":30.72389487346709,"speed":20,"pause":0,"$$hashKey":"object:42"},{"latitude":46.485256741040565,"longitude":30.727244050692207,"speed":20,"pause":0,"$$hashKey":"object:43"},{"latitude":46.48573452094652,"longitude":30.728619127009438,"speed":20,"pause":0,"$$hashKey":"object:44"},{"latitude":46.487586634240195,"longitude":30.72946312490285,"speed":20,"pause":0,"$$hashKey":"object:45"},{"latitude":46.48668876881446,"longitude":30.727589013344073,"speed":20,"pause":0,"$$hashKey":"object:46"},{"latitude":46.48701544727699,"longitude":30.72352989353726,"$$hashKey":"object:1699","$selected":true,"speed":20},{"latitude":46.486943166256104,"longitude":30.7223246318124,"speed":20,"pause":0,"$$hashKey":"object:47"},{"latitude":46.4891511891017,"longitude":30.730185025899686,"speed":20,"pause":0,"$$hashKey":"object:48"},{"latitude":46.4892949745091,"longitude":30.72782833905626,"speed":20,"pause":0,"$$hashKey":"object:49"},{"latitude":46.49066689516103,"longitude":30.725748718360933,"speed":20,"pause":0,"$$hashKey":"object:50"},{"latitude":46.49201763746595,"longitude":30.719065494392225,"speed":20,"pause":0,"$$hashKey":"object:51"},{"latitude":46.492560109790816,"longitude":30.719221418917414,"speed":20,"pause":0,"$$hashKey":"object:52"},{"latitude":46.49580052440313,"longitude":30.71850546514338,"speed":20,"pause":0,"$$hashKey":"object:53"},{"latitude":46.4936391135135,"longitude":30.7225678718645,"speed":20,"pause":0,"$$hashKey":"object:54"},{"latitude":46.492868557394395,"longitude":30.725865014416968,"speed":20,"pause":0,"$$hashKey":"object:55"},{"latitude":46.494107010017565,"longitude":30.725771858557664,"speed":20,"pause":0,"$$hashKey":"object:56"},{"latitude":46.49332453883087,"longitude":30.726622871876657,"speed":20,"pause":0,"$$hashKey":"object:57"},{"latitude":46.49366474422872,"longitude":30.72816052099074,"speed":20,"pause":0,"$$hashKey":"object:58"},{"latitude":46.4946253531108,"longitude":30.72922608911233,"speed":20,"pause":0,"$$hashKey":"object:59"},{"latitude":46.49328131598641,"longitude":30.732183586092788,"speed":20,"pause":0,"$$hashKey":"object:60"},{"latitude":46.49450756823097,"longitude":30.73458317779705,"speed":20,"pause":0,"$$hashKey":"object:61"},{"latitude":46.4931271288483,"longitude":30.735812900262317,"speed":20,"pause":0,"$$hashKey":"object:62"},{"latitude":46.491480878108156,"longitude":30.738051122026718,"speed":20,"pause":0,"$$hashKey":"object:63"},{"latitude":46.489189027093936,"longitude":30.739126788540943,"speed":20,"pause":0,"$$hashKey":"object:64"},{"latitude":46.49017681809899,"longitude":30.74003076994552,"speed":20,"pause":0,"$$hashKey":"object:65"},{"latitude":46.49011370702476,"longitude":30.745336335175807,"speed":20,"pause":0,"$$hashKey":"object:66"},{"latitude":46.48891567684178,"longitude":30.74145320696266,"speed":20,"pause":0,"$$hashKey":"object:67"},{"latitude":46.48755371999257,"longitude":30.740210004191795,"speed":20,"pause":0,"$$hashKey":"object:68"},{"latitude":46.48747428402808,"longitude":30.74072767490975,"speed":20,"pause":0,"$$hashKey":"object:69"},{"latitude":46.48728685535574,"longitude":30.74478990711407,"speed":20,"pause":0,"$$hashKey":"object:70"},{"latitude":46.48475029150085,"longitude":30.74567627994361,"speed":20,"pause":0,"$$hashKey":"object:71"},{"latitude":46.484700952054844,"longitude":30.744301011073276,"speed":20,"pause":0,"$$hashKey":"object:72"},{"latitude":46.485700576723424,"longitude":30.74193865664006,"speed":20,"pause":0,"$$hashKey":"object:73"},{"latitude":46.484848500457375,"longitude":30.740982757533402,"speed":20,"pause":0,"$$hashKey":"object:74"},{"latitude":46.48503560353821,"longitude":30.73927100584342,"speed":20,"pause":0,"$$hashKey":"object:75"},{"latitude":46.48426234812743,"longitude":30.739018386440193,"speed":20,"pause":0,"$$hashKey":"object:76"},{"latitude":46.484865531045244,"longitude":30.737923062567916,"speed":20,"pause":0,"$$hashKey":"object:77"},{"tag":"","latitude":"46.485055","longitude":"30.735669","speed":20,"pause":0,"$$hashKey":"object:78"}]